LICENSE
MANIFEST.in
README.md
settings.ini
setup.py
parag/__init__.py
parag/_modidx.py
parag/core.py
parag/graph.py
parag/hypergraph.py
parag/utils.py
parag.egg-info/PKG-INFO
parag.egg-info/SOURCES.txt
parag.egg-info/dependency_links.txt
parag.egg-info/entry_points.txt
parag.egg-info/not-zip-safe
parag.egg-info/requires.txt
parag.egg-info/top_level.txt