Metadata-Version: 2.1
Name: parag
Version: 0.0.1
Summary: parag: interactive visualization of higher-order graphs in Python
Home-page: https://github.com/rraadd88/parag
Author: Rohan Dandage
Author-email: rohanadanadge@gmail.com
License: Apache Software License 2.0
Keywords: nbdev jupyter notebook python
Classifier: Development Status :: 4 - Beta
Classifier: Intended Audience :: Developers
Classifier: Natural Language :: English
Classifier: Programming Language :: Python :: 3.7
Classifier: Programming Language :: Python :: 3.8
Classifier: Programming Language :: Python :: 3.9
Classifier: Programming Language :: Python :: 3.10
Classifier: License :: OSI Approved :: Apache Software License
Requires-Python: >=3.7
License-File: LICENSE
Requires-Dist: roux
Requires-Dist: networkx
Requires-Dist: vl-convert-python
Provides-Extra: dev
Requires-Dist: scanpy; extra == "dev"
